odoo/addons/mrp_request_workcenter_cycle/README.rst
odoo/addons/mrp_request_workcenter_cycle/__init__.py
odoo/addons/mrp_request_workcenter_cycle/__manifest__.py
odoo/addons/mrp_request_workcenter_cycle/demo/request.xml
odoo/addons/mrp_request_workcenter_cycle/demo/workcenter.xml
odoo/addons/mrp_request_workcenter_cycle/i18n/mrp_request_workcenter_cycle.pot
odoo/addons/mrp_request_workcenter_cycle/i18n/pt_BR.po
odoo/addons/mrp_request_workcenter_cycle/models/__init__.py
odoo/addons/mrp_request_workcenter_cycle/models/product.py
odoo/addons/mrp_request_workcenter_cycle/models/product_workcenter_quantity.py
odoo/addons/mrp_request_workcenter_cycle/models/request.py
odoo/addons/mrp_request_workcenter_cycle/models/request_workcenter.py
odoo/addons/mrp_request_workcenter_cycle/readme/CONFIGURE.rst
odoo/addons/mrp_request_workcenter_cycle/readme/CONTRIBUTORS.rst
odoo/addons/mrp_request_workcenter_cycle/readme/DESCRIPTION.rst
odoo/addons/mrp_request_workcenter_cycle/readme/ROADMAP.rst
odoo/addons/mrp_request_workcenter_cycle/readme/USAGE.rst
odoo/addons/mrp_request_workcenter_cycle/security/ir.model.access.csv
odoo/addons/mrp_request_workcenter_cycle/static/description/icon.png
odoo/addons/mrp_request_workcenter_cycle/static/description/index.html
odoo/addons/mrp_request_workcenter_cycle/static/description/request.png
odoo/addons/mrp_request_workcenter_cycle/static/description/settings.png
odoo/addons/mrp_request_workcenter_cycle/tests/__init__.py
odoo/addons/mrp_request_workcenter_cycle/tests/test_cycle.py
odoo/addons/mrp_request_workcenter_cycle/views/product.xml
odoo/addons/mrp_request_workcenter_cycle/views/request.xml
odoo/addons/mrp_request_workcenter_cycle/wizards/__init__.py
odoo/addons/mrp_request_workcenter_cycle/wizards/request_create_mo.py
odoo12_addon_mrp_request_workcenter_cycle-12.0.1.0.1.dist-info/METADATA
odoo12_addon_mrp_request_workcenter_cycle-12.0.1.0.1.dist-info/WHEEL
odoo12_addon_mrp_request_workcenter_cycle-12.0.1.0.1.dist-info/top_level.txt
odoo12_addon_mrp_request_workcenter_cycle-12.0.1.0.1.dist-info/RECORD
