Metadata-Version: 2.1
Name: odoo12-addon-mrp-request-workcenter-cycle
Version: 12.0.1.0.1
Summary: MRP Request Workcenter Cycle
Home-page: https://github.com/OCA/manufacture/mrp_request_workcenter_cycle
Author: Akretion, Odoo Community Association (OCA)
Author-email: support@odoo-community.org
License: AGPL-3
Platform: UNKNOWN
Classifier: Programming Language :: Python
Classifier: Framework :: Odoo
Classifier: Framework :: Odoo :: 12.0
Classifier: License :: OSI Approved :: GNU Affero General Public License v3
Classifier: Development Status :: 3 - Alpha
Requires-Python: >=3.5
Requires-Dist: odoo12-addon-mrp-production-request
Requires-Dist: odoo (<12.1dev,>=12.0a)
